python_mbedtls-2.10.1.dist-info/LICENSE.txt
python_mbedtls-2.10.1.dist-info/METADATA
python_mbedtls-2.10.1.dist-info/RECORD
python_mbedtls-2.10.1.dist-info/top_level.txt
python_mbedtls-2.10.1.dist-info/WHEEL
mbedtls/hmac.py
mbedtls/version.cpython-39-i386-linux-gnu.so
mbedtls/pk.pyi
mbedtls/hkdf.cpython-39-i386-linux-gnu.so
mbedtls/_random.pyi
mbedtls/secrets.py
mbedtls/py.typed
mbedtls/exceptions.cpython-39-i386-linux-gnu.so
mbedtls/_ringbuf.cpython-39-i386-linux-gnu.so
mbedtls/hkdf.pyi
mbedtls/mpi.pyi
mbedtls/_random.cpython-39-i386-linux-gnu.so
mbedtls/_tlsi.py
mbedtls/_tls.cpython-39-i386-linux-gnu.so
mbedtls/_platform.cpython-39-i386-linux-gnu.so
mbedtls/x509.cpython-39-i386-linux-gnu.so
mbedtls/tls.py
mbedtls/_md.cpython-39-i386-linux-gnu.so
mbedtls/__init__.py
mbedtls/x509.pyi
mbedtls/_platform.pyi
mbedtls/_tls.pyi
mbedtls/_md.pyi
mbedtls/hashlib.py
mbedtls/exceptions.pyi
mbedtls/pk.cpython-39-i386-linux-gnu.so
mbedtls/version.pyi
mbedtls/mpi.cpython-39-i386-linux-gnu.so
mbedtls/cipher/_cipher.pyi
mbedtls/cipher/CHACHA20.py
mbedtls/cipher/DES3dbl.py
mbedtls/cipher/ARC4.py
mbedtls/cipher/_cipher.cpython-39-i386-linux-gnu.so
mbedtls/cipher/AES.py
mbedtls/cipher/DES3.py
mbedtls/cipher/__init__.py
mbedtls/cipher/Blowfish.py
mbedtls/cipher/Camellia.py
mbedtls/cipher/ARIA.py
mbedtls/cipher/DES.py
python_mbedtls.libs/libmbedx509-dd985808.so.1
python_mbedtls.libs/libmbedtls-7a76d6d5.so.14
python_mbedtls.libs/libmbedcrypto-a88abcfb.so.7
