Metadata-Version: 2.1
Name: python-mbedtls
Version: 2.10.1
Summary: hash, hmac, RSA, ECC, X.509, TLS, DTLS, handshakes, and secrets with an mbed TLS back end
Home-page: https://github.com/Synss/python-mbedtls
Download-URL: https://github.com/Synss/python-mbedtls/tarball/2.10.1
Author: Mathias Laurin
Author-email: Mathias.Laurin@github.com
License: MIT License
Classifier: Development Status :: 5 - Production/Stable
Classifier: Programming Language :: Cython
Classifier: Programming Language :: Python :: 3
Classifier: License :: OSI Approved :: MIT License
Classifier: Topic :: Security :: Cryptography
License-File: LICENSE.txt
Requires-Dist: certifi
Requires-Dist: typing-extensions
